fifo.sv
module FIFO (
    input logic clk,
    input logic rst,
    input logic read_data,
    input logic write_data,
    input logic [7:0] data_input,
    output logic [7:0] data_output,
    output logic full, // memory full flag
    output logic empty // memory empty flag
);

parameter DEPTH = 16;
parameter add_ptr = ($clog2(DEPTH));
reg [7:0] mem [0:DEPTH-1]; // location start from 0 and end 15, each locations are capable to store 8 bit
reg [add_ptr-1: 0]read_ptr;
reg [add_ptr-1: 0]write_ptr;
reg [DEPTH :0] counter; // counter to count 0 to 16. One bit more to write at 15th location.

// combination logic for flag update;
assign full = (counter == DEPTH);
assign empty = (counter == 0);

//sequencial block

always_ff @( posedge clk ) begin 
    if (rst) begin
        for (int i =0 ;i<DEPTH;i++ ) begin
            mem[i] <= 0;
        end
        read_ptr <= 0;
        write_ptr <= 0;
        counter <= 0;
        data_output <= 0;
    end else begin
        if (write_data && !full) begin
            mem[write_ptr] <= data_input;
            write_ptr <= write_ptr +1;
            counter <= counter+1;
        end else if (read_data && !empty) begin
            data_output <= mem[read_ptr];
            read_ptr <= read_ptr + 1;
            counter <= counter -1;
        end
    end
end
    
endmodule

fifo_tb.sv
`timescale 1ns/1ps
`include "fifo.sv"
module tb;

    logic clk;
    logic rst;
    logic read_data;
    logic write_data;
    logic [7:0] data_input;
    logic [7:0] data_output;
    logic full; // memory full flag
    logic empty;
    parameter PERIOD = 10;
FIFO DUT (
    .clk(clk),
    .rst (rst),
    .write_data(write_data),
    .read_data(read_data),
    .data_input(data_input),
    .data_output(data_output),
    .full(full),
    .empty(empty)
);

function void show();
$display("%0d  | %b   | %b   | %b  | %b  | %d       | %d        | %b    | %b     | %0d",
                 $time, clk, rst, write_data, read_data, data_input, data_output, full, empty, DUT.counter); // Display initial state
    
endfunction
function void title();
    $display("------------------------------------------------------------------------------------------------------------------");
    $display("Time   | clk | rst | WR | RD | Data In   | Data Out   | Full | Empty | FIFO_Count");
    $display("------------------------------------------------------------------------------------------------------------------");

endfunction

initial begin
    clk = 0;
    forever #(PERIOD/2) clk = ~clk;
end

initial begin
    rst = 1;
    read_data =0;
    write_data =0;
    data_input ='0;
    // Display header for console output
    title();
    @(posedge clk);
    #1;
    show();
    rst = 0; // Release reset
    $display("[%0t] Reset released.", $time);

     // --- Scenario 1: Write multiple items into the FIFO ---
    $display("\n--- Scenario 1: Writing data into FIFO ---");
    title();
    repeat (DUT.DEPTH/2) begin
      @(posedge clk);
      #1;
        write_data =1;
        read_data =0;
        data_input = $urandom_range (255,1);
        show();
    end
    // --- Scenario 2: Read some data from the FIFO ---
    $display("\n--- Scenario 2: Reading data from FIFO ---");
    title();
    repeat (DUT.DEPTH/4) begin
        @(posedge clk);
        #1;
        read_data =1;
        write_data =0;
        data_input = '0;
        show();

    end
    $display("-----Reading data disable-----");
    @(posedge clk);
    #1;
    read_data = 0;
    title();
    show();
    #(PERIOD);
    // --- Scenario 3: Fill the FIFO completely and check 'full' flag ---
    $display("\n--- Scenario 3: Filling FIFO to FULL ---");
    title();
    repeat (DUT.DEPTH +2) begin
        @(posedge clk);
        #1;
        write_data =1;
        read_data =0;
        data_input = $urandom_range (255,1);
        show();
        if (write_data && full) begin
            $display("[%0d] **INFO: FIFO is FULL. Subsequent writes should be ignored by DUT.**", $time);
        end
    end
    $display("-----Writing data disable-----");
    @(posedge clk);
    #1;
    write_data = 0;
    title();
    show();
    #(PERIOD);





    // --- Scenario 4: Empty the FIFO completely and check 'empty' flag ---
    $display("\n--- Scenario 4: Emptying FIFO to EMPTY ---");
    title();
    repeat (DUT.DEPTH +2) begin // read to 2 more
        @(posedge clk);
        #1;
        read_data =1;
        write_data =0;
        data_input = '0;
        show();
        if (read_data && empty) begin
            $display("[%0d] **INFO: FIFO is EMPTY. Subsequent READS should be ignored by DUT.**", $time);
        end

    end

    $display("-----Reading data disable-----");
    @(posedge clk);
    #1;
    read_data = 0;
    title();
    show();
    #(PERIOD*5);// final delay

    $display("[%0d] Testbench: Simulation complete.", $time);
    $finish; // End the simulation

    end


initial begin
    $dumpfile("dump.vcd");
    $dumpvars;
end


endmodule

dump.vcd
$date
	Sun Jul 20 22:47:26 2025
$end
$version
	Icarus Verilog
$end
$timescale
	1ps
$end
$scope module tb $end
$var wire 1 ! full $end
$var wire 1 " empty $end
$var wire 8 # data_output [7:0] $end
$var parameter 32 $ PERIOD $end
$var reg 1 % clk $end
$var reg 8 & data_input [7:0] $end
$var reg 1 ' read_data $end
$var reg 1 ( rst $end
$var reg 1 ) write_data $end
$scope function show $end
$upscope $end
$scope function title $end
$upscope $end
$scope module DUT $end
$var wire 1 % clk $end
$var wire 8 * data_input [7:0] $end
$var wire 1 ' read_data $end
$var wire 1 ( rst $end
$var wire 1 ) write_data $end
$var wire 1 ! full $end
$var wire 1 " empty $end
$var parameter 32 + DEPTH $end
$var parameter 32 , add_ptr $end
$var reg 17 - counter [16:0] $end
$var reg 8 . data_output [7:0] $end
$var reg 4 / read_ptr [3:0] $end
$var reg 4 0 write_ptr [3:0] $end
$scope begin $ivl_for_loop0 $end
$var integer 32 1 i [31:0] $end
$upscope $end
$upscope $end
$upscope $end
$enddefinitions $end
$comment Show the parameter values. $end
$dumpall
b100 ,
b10000 +
b1010 $
$end
#0
$dumpvars
b0 1
bx 0
bx /
bx .
bx -
b0 *
0)
1(
0'
b0 &
0%
bx #
x"
x!
$end
#5000
b0 #
b0 .
0!
1"
b0 -
b0 0
b0 /
b10000 1
1%
#6000
0(
#10000
0%
#15000
1%
#16000
b10010010 &
b10010010 *
1)
#20000
0%
#25000
0"
b1 -
b1 0
1%
#26000
b1000001 &
b1000001 *
#30000
0%
#35000
b10 -
b10 0
1%
#36000
b101 &
b101 *
#40000
0%
#45000
b11 -
b11 0
1%
#46000
b110010 &
b110010 *
#50000
0%
#55000
b100 -
b100 0
1%
#56000
b10000111 &
b10000111 *
#60000
0%
#65000
b101 -
b101 0
1%
#66000
b11000111 &
b11000111 *
#70000
0%
#75000
b110 -
b110 0
1%
#76000
b110011 &
b110011 *
#80000
0%
#85000
b111 -
b111 0
1%
#86000
b1010 &
b1010 *
#90000
0%
#95000
b1000 -
b1000 0
1%
#96000
b0 &
b0 *
0)
1'
#100000
0%
#105000
b111 -
b1 /
b10010010 #
b10010010 .
1%
#110000
0%
#115000
b110 -
b10 /
b1000001 #
b1000001 .
1%
#120000
0%
#125000
b101 -
b11 /
b101 #
b101 .
1%
#130000
0%
#135000
b100 -
b100 /
b110010 #
b110010 .
1%
#136000
0'
#140000
0%
#145000
1%
#150000
0%
#155000
1%
#156000
b10000001 &
b10000001 *
1)
#160000
0%
#165000
b101 -
b1001 0
1%
#166000
b10000111 &
b10000111 *
#170000
0%
#175000
b110 -
b1010 0
1%
#176000
b10111011 &
b10111011 *
#180000
0%
#185000
b111 -
b1011 0
1%
#186000
b10011110 &
b10011110 *
#190000
0%
#195000
b1000 -
b1100 0
1%
#196000
b11110110 &
b11110110 *
#200000
0%
#205000
b1001 -
b1101 0
1%
#206000
b11000110 &
b11000110 *
#210000
0%
#215000
b1010 -
b1110 0
1%
#216000
b11111101 &
b11111101 *
#220000
0%
#225000
b1011 -
b1111 0
1%
#226000
b1100011 &
b1100011 *
#230000
0%
#235000
b1100 -
b0 0
1%
#240000
0%
#245000
b1101 -
b1 0
1%
#246000
b1010101 &
b1010101 *
#250000
0%
#255000
b1110 -
b10 0
1%
#256000
b11110010 &
b11110010 *
#260000
0%
#265000
b1111 -
b11 0
1%
#266000
b111100 &
b111100 *
#270000
0%
#275000
1!
b10000 -
b100 0
1%
#276000
b1010 &
b1010 *
#280000
0%
#285000
1%
#286000
b11001000 &
b11001000 *
#290000
0%
#295000
1%
#296000
b11111001 &
b11111001 *
#300000
0%
#305000
1%
#306000
b1101000 &
b1101000 *
#310000
0%
#315000
1%
#316000
b1110100 &
b1110100 *
#320000
0%
#325000
1%
#326000
b1100011 &
b1100011 *
#330000
0%
#335000
1%
#336000
0)
#340000
0%
#345000
1%
#350000
0%
#355000
1%
#356000
b0 &
b0 *
1'
#360000
0%
#365000
0!
b1111 -
b101 /
b10000111 #
b10000111 .
1%
#370000
0%
#375000
b1110 -
b110 /
b11000111 #
b11000111 .
1%
#380000
0%
#385000
b1101 -
b111 /
b110011 #
b110011 .
1%
#390000
0%
#395000
b1100 -
b1000 /
b1010 #
b1010 .
1%
#400000
0%
#405000
b1011 -
b1001 /
b10000001 #
b10000001 .
1%
#410000
0%
#415000
b1010 -
b1010 /
b10000111 #
b10000111 .
1%
#420000
0%
#425000
b1001 -
b1011 /
b10111011 #
b10111011 .
1%
#430000
0%
#435000
b1000 -
b1100 /
b10011110 #
b10011110 .
1%
#440000
0%
#445000
b111 -
b1101 /
b11110110 #
b11110110 .
1%
#450000
0%
#455000
b110 -
b1110 /
b11000110 #
b11000110 .
1%
#460000
0%
#465000
b101 -
b1111 /
b11111101 #
b11111101 .
1%
#470000
0%
#475000
b100 -
b0 /
b1100011 #
b1100011 .
1%
#480000
0%
#485000
b11 -
b1 /
1%
#490000
0%
#495000
b10 -
b10 /
b1010101 #
b1010101 .
1%
#500000
0%
#505000
b1 -
b11 /
b11110010 #
b11110010 .
1%
#510000
0%
#515000
1"
b0 -
b100 /
b111100 #
b111100 .
1%
#520000
0%
#525000
1%
#530000
0%
#535000
1%
#536000
0'
